pynepcord/__init__.py
pynepcord/__main__.py
pynepcord/errors.py
pynepcord/models.py
pynepcord/aio/__init__.py
pynepcord/aio/images.py
pynepcord/aio/sharp.py
pynepcord/base/__init__.py
pynepcord/base/images.py
pynepcord/base/sharp.py
pynepcord-1.0.1.dist-info/LICENSE
pynepcord-1.0.1.dist-info/METADATA
pynepcord-1.0.1.dist-info/WHEEL
pynepcord-1.0.1.dist-info/top_level.txt
pynepcord-1.0.1.dist-info/RECORD
