Metadata-Version: 2.1
Name: pynepcord
Version: 1.0.1
Summary: Python SDK for the NeppedCord API
Home-page: https://github.com/NellyD3v/pynepcord
Author: NellyD3v
License: MIT
Platform: UNKNOWN
Classifier: Programming Language :: Python :: 3
Classifier: Programming Language :: Python :: 3.6
Classifier: Programming Language :: Python :: 3.7
Classifier: Programming Language :: Python :: 3.8
Classifier: Programming Language :: Python :: 3.9
Requires-Dist: requests
Requires-Dist: aiohttp
